fighting_sound/sound_manager.py
fighting_sound/models/audio_buffer.py
fighting_sound/models/audio_source.py
fighting_sound/models/sound_renderer.py
fighting_sound/openal/__init__.py
fighting_sound/openal/al.py
fighting_sound/openal/alc.py
fighting_sound/openal/log.py
fighting_sound/openal/soft.py
fighting_sound/utils/dtype.py
fighting_sound/utils/openal.py
fighting_sound/utils/wave.py
fighting_sound-0.5.dist-info/METADATA
fighting_sound-0.5.dist-info/WHEEL
fighting_sound-0.5.dist-info/top_level.txt
fighting_sound-0.5.dist-info/RECORD
