Metadata-Version: 2.1
Name: fighting-sound
Version: 0.5
Summary: A sound library for DareFightingICE with OpenAL backend
Author: yan
Project-URL: Homepage, https://github.com/yan-2/pyftg-sound
Project-URL: Issues, https://github.com/yan-2/pyftg-sound/issues
Classifier: Programming Language :: Python :: 3
Classifier: License :: OSI Approved :: MIT License
Classifier: Operating System :: OS Independent
Requires-Python: >=3.10
Requires-Dist: numpy ~=1.26.4
